desota/__init__.py
desota/detools.py
desota-0.0.5.dist-info/LICENSE
desota-0.0.5.dist-info/METADATA
desota-0.0.5.dist-info/WHEEL
desota-0.0.5.dist-info/top_level.txt
desota-0.0.5.dist-info/RECORD
