Metadata-Version: 2.1
Name: desota
Version: 0.0.5
Summary: DeSOTA Tools Package
Author-email: Francisco Vargas <87917356+franciscomvargas@users.noreply.github.com>, Kristian Atanasov <27017759+spacewalkingninja@users.noreply.github.com>
Project-URL: Homepage, https://github.com/desotaai/pip
Project-URL: Issues, https://github.com/DeSOTAai/pip/issues
Classifier: Programming Language :: Python :: 3
Classifier: License :: OSI Approved :: MIT License
Classifier: Operating System :: OS Independent
Requires-Python: >=3.7
License-File: LICENSE
Requires-Dist: requests
Requires-Dist: pyyaml
